{
    "version": "1.3.9",
    "architecture": {
        "64bit": {
            "url": "https://github.com/bengarrett/zipcmt/releases/download/v1.3.9/zipcmt_Windows_Intel.zip",
            "bin": [
                "zipcmt.exe"
            ],
            "hash": "2237bbe1216c7a4983534bfdf18a9643c835126e4121afab9c4319cc43dd78cc"
        }
    },
    "homepage": "https://github.com/bengarrett/zipcmt/",
    "license": "LGPL 3.0",
    "description": "A batch viewer and extractor for large collections of zip archives."
}